timeback/__init__.py
timeback/py.typed
timeback/server/__init__.py
timeback/server/timeback.py
timeback/server/types.py
timeback/server/adapters/__init__.py
timeback/server/adapters/django.py
timeback/server/adapters/fastapi.py
timeback/server/handlers/__init__.py
timeback/server/handlers/factory.py
timeback/server/handlers/activity/__init__.py
timeback/server/handlers/activity/attempts.py
timeback/server/handlers/activity/caliper.py
timeback/server/handlers/activity/completion.py
timeback/server/handlers/activity/handler.py
timeback/server/handlers/activity/progress.py
timeback/server/handlers/activity/resolve.py
timeback/server/handlers/activity/schema.py
timeback/server/handlers/identity/__init__.py
timeback/server/handlers/identity/handler.py
timeback/server/handlers/identity_only/__init__.py
timeback/server/handlers/identity_only/handler.py
timeback/server/handlers/user/__init__.py
timeback/server/handlers/user/enrollments.py
timeback/server/handlers/user/handler.py
timeback/server/handlers/user/profile.py
timeback/server/handlers/user/verify.py
timeback/server/lib/__init__.py
timeback/server/lib/logger.py
timeback/server/lib/oidc.py
timeback/server/lib/resolve.py
timeback/server/lib/utils.py
timeback/shared/__init__.py
timeback/shared/constants.py
timeback/shared/types.py
timeback/shared/xp_calculator.py
timeback_sdk-0.1.4.dist-info/METADATA
timeback_sdk-0.1.4.dist-info/WHEEL
timeback_sdk-0.1.4.dist-info/RECORD
