Metadata-Version: 2.4
Name: timeback-sdk
Version: 0.1.4
Summary: Timeback SDK for Python - adapters for FastAPI, Django, and more
Project-URL: Homepage, https://developer.timeback.com
Project-URL: Documentation, https://docs.timeback.com
Project-URL: Repository, https://github.com/superbuilders/timeback-dev-python
Author-email: Timeback <dev@timeback.dev>
License-Expression: MIT
Classifier: Development Status :: 3 - Alpha
Classifier: Intended Audience :: Developers
Classifier: License :: OSI Approved :: MIT License
Classifier: Programming Language :: Python :: 3
Classifier: Programming Language :: Python :: 3.12
Classifier: Programming Language :: Python :: 3.13
Classifier: Typing :: Typed
Requires-Python: >=3.12
Requires-Dist: httpx>=0.27.0
Requires-Dist: starlette>=0.35.0
Requires-Dist: timeback-common>=0.1.0
Requires-Dist: timeback-core>=0.1.0
Provides-Extra: dev
Requires-Dist: pytest-asyncio>=0.23; extra == 'dev'
Requires-Dist: pytest>=8.0; extra == 'dev'
Requires-Dist: ruff>=0.8.0; extra == 'dev'
Provides-Extra: django
Requires-Dist: django>=4.0; extra == 'django'
Provides-Extra: fastapi
Requires-Dist: fastapi>=0.100.0; extra == 'fastapi'
